{
  "version": "6",
  "dialect": "sqlite",
  "id": "99d9653a-e14d-4734-b52f-bcf7d6c3230b",
  "prevId": "f12dff47-d1a1-4c50-b8d7-07f87dff803c",
  "tables": {
    "app_state": {
      "name": "app_state",
      "columns": {
        "key": {
          "name": "key",
          "type": "text",
          "primaryKey": true,
          "notNull": true,
          "autoincrement": false
        },
        "value": {
          "name": "value",
          "type": "text",
          "primaryKey": false,
          "notNull": false,
          "autoincrement": false
        }
      },
      "indexes": {},
      "foreignKeys": {},
      "compositePrimaryKeys": {},
      "uniqueConstraints": {},
      "checkConstraints": {}
    },
    "card_progress": {
      "name": "card_progress",
      "columns": {
        "id": {
          "name": "id",
          "type": "integer",
          "primaryKey": true,
          "notNull": true,
          "autoincrement": true
        },
        "user_id": {
          "name": "user_id",
          "type": "integer",
          "primaryKey": false,
          "notNull": true,
          "autoincrement": false
        },
        "word_id": {
          "name": "word_id",
          "type": "integer",
          "primaryKey": false,
          "notNull": true,
          "autoincrement": false
        },
        "stability": {
          "name": "stability",
          "type": "real",
          "primaryKey": false,
          "notNull": true,
          "autoincrement": false,
          "default": 0
        },
        "difficulty": {
          "name": "difficulty",
          "type": "real",
          "primaryKey": false,
          "notNull": true,
          "autoincrement": false,
          "default": 0.3
        },
        "elapsed_days": {
          "name": "elapsed_days",
          "type": "real",
          "primaryKey": false,
          "notNull": true,
          "autoincrement": false,
          "default": 0
        },
        "scheduled_days": {
          "name": "scheduled_days",
          "type": "real",
          "primaryKey": false,
          "notNull": true,
          "autoincrement": false,
          "default": 0
        },
        "reps": {
          "name": "reps",
          "type": "integer",
          "primaryKey": false,
          "notNull": true,
          "autoincrement": false,
          "default": 0
        },
        "lapses": {
          "name": "lapses",
          "type": "integer",
          "primaryKey": false,
          "notNull": true,
          "autoincrement": false,
          "default": 0
        },
        "state": {
          "name": "state",
          "type": "integer",
          "primaryKey": false,
          "notNull": true,
          "autoincrement": false,
          "default": 0
        },
        "due_date": {
          "name": "due_date",
          "type": "integer",
          "primaryKey": false,
          "notNull": true,
          "autoincrement": false
        },
        "last_reviewed_at": {
          "name": "last_reviewed_at",
          "type": "integer",
          "primaryKey": false,
          "notNull": false,
          "autoincrement": false
        },
        "total_attempts": {
          "name": "total_attempts",
          "type": "integer",
          "primaryKey": false,
          "notNull": true,
          "autoincrement": false,
          "default": 0
        },
        "correct_attempts": {
          "name": "correct_attempts",
          "type": "integer",
          "primaryKey": false,
          "notNull": true,
          "autoincrement": false,
          "default": 0
        },
        "average_levenshtein": {
          "name": "average_levenshtein",
          "type": "real",
          "primaryKey": false,
          "notNull": false,
          "autoincrement": false,
          "default": 0
        },
        "created_at": {
          "name": "created_at",
          "type": "integer",
          "primaryKey": false,
          "notNull": true,
          "autoincrement": false
        },
        "updated_at": {
          "name": "updated_at",
          "type": "integer",
          "primaryKey": false,
          "notNull": true,
          "autoincrement": false
        }
      },
      "indexes": {
        "card_progress_due_date_idx": {
          "name": "card_progress_due_date_idx",
          "columns": [
            "due_date"
          ],
          "isUnique": false
        },
        "card_progress_state_idx": {
          "name": "card_progress_state_idx",
          "columns": [
            "state"
          ],
          "isUnique": false
        },
        "card_progress_user_id_idx": {
          "name": "card_progress_user_id_idx",
          "columns": [
            "user_id"
          ],
          "isUnique": false
        },
        "card_progress_user_word_unique": {
          "name": "card_progress_user_word_unique",
          "columns": [
            "user_id",
            "word_id"
          ],
          "isUnique": true
        }
      },
      "foreignKeys": {
        "card_progress_user_id_user_profile_id_fk": {
          "name": "card_progress_user_id_user_profile_id_fk",
          "tableFrom": "card_progress",
          "tableTo": "user_profile",
          "columnsFrom": [
            "user_id"
          ],
          "columnsTo": [
            "id"
          ],
          "onDelete": "cascade",
          "onUpdate": "no action"
        },
        "card_progress_word_id_words_id_fk": {
          "name": "card_progress_word_id_words_id_fk",
          "tableFrom": "card_progress",
          "tableTo": "words",
          "columnsFrom": [
            "word_id"
          ],
          "columnsTo": [
            "id"
          ],
          "onDelete": "cascade",
          "onUpdate": "no action"
        }
      },
      "compositePrimaryKeys": {},
      "uniqueConstraints": {},
      "checkConstraints": {}
    },
    "daily_progress": {
      "name": "daily_progress",
      "columns": {
        "id": {
          "name": "id",
          "type": "integer",
          "primaryKey": true,
          "notNull": true,
          "autoincrement": true
        },
        "user_id": {
          "name": "user_id",
          "type": "integer",
          "primaryKey": false,
          "notNull": true,
          "autoincrement": false
        },
        "date": {
          "name": "date",
          "type": "integer",
          "primaryKey": false,
          "notNull": true,
          "autoincrement": false
        },
        "words_reviewed": {
          "name": "words_reviewed",
          "type": "integer",
          "primaryKey": false,
          "notNull": true,
          "autoincrement": false,
          "default": 0
        },
        "words_learned": {
          "name": "words_learned",
          "type": "integer",
          "primaryKey": false,
          "notNull": true,
          "autoincrement": false,
          "default": 0
        },
        "minutes_practiced": {
          "name": "minutes_practiced",
          "type": "integer",
          "primaryKey": false,
          "notNull": true,
          "autoincrement": false,
          "default": 0
        },
        "goal_met": {
          "name": "goal_met",
          "type": "integer",
          "primaryKey": false,
          "notNull": true,
          "autoincrement": false,
          "default": 0
        }
      },
      "indexes": {
        "daily_progress_date_idx": {
          "name": "daily_progress_date_idx",
          "columns": [
            "date"
          ],
          "isUnique": false
        },
        "daily_progress_user_date_unique": {
          "name": "daily_progress_user_date_unique",
          "columns": [
            "user_id",
            "date"
          ],
          "isUnique": true
        }
      },
      "foreignKeys": {
        "daily_progress_user_id_user_profile_id_fk": {
          "name": "daily_progress_user_id_user_profile_id_fk",
          "tableFrom": "daily_progress",
          "tableTo": "user_profile",
          "columnsFrom": [
            "user_id"
          ],
          "columnsTo": [
            "id"
          ],
          "onDelete": "cascade",
          "onUpdate": "no action"
        }
      },
      "compositePrimaryKeys": {},
      "uniqueConstraints": {},
      "checkConstraints": {}
    },
    "quiz_attempts": {
      "name": "quiz_attempts",
      "columns": {
        "id": {
          "name": "id",
          "type": "integer",
          "primaryKey": true,
          "notNull": true,
          "autoincrement": true
        },
        "session_id": {
          "name": "session_id",
          "type": "integer",
          "primaryKey": false,
          "notNull": true,
          "autoincrement": false
        },
        "card_progress_id": {
          "name": "card_progress_id",
          "type": "integer",
          "primaryKey": false,
          "notNull": true,
          "autoincrement": false
        },
        "word_id": {
          "name": "word_id",
          "type": "integer",
          "primaryKey": false,
          "notNull": true,
          "autoincrement": false
        },
        "user_input": {
          "name": "user_input",
          "type": "text",
          "primaryKey": false,
          "notNull": true,
          "autoincrement": false
        },
        "is_correct": {
          "name": "is_correct",
          "type": "integer",
          "primaryKey": false,
          "notNull": true,
          "autoincrement": false
        },
        "levenshtein_distance": {
          "name": "levenshtein_distance",
          "type": "integer",
          "primaryKey": false,
          "notNull": true,
          "autoincrement": false
        },
        "normalized_error": {
          "name": "normalized_error",
          "type": "real",
          "primaryKey": false,
          "notNull": true,
          "autoincrement": false
        },
        "fsrs_rating": {
          "name": "fsrs_rating",
          "type": "integer",
          "primaryKey": false,
          "notNull": true,
          "autoincrement": false
        },
        "response_time_ms": {
          "name": "response_time_ms",
          "type": "integer",
          "primaryKey": false,
          "notNull": false,
          "autoincrement": false
        },
        "attempted_at": {
          "name": "attempted_at",
          "type": "integer",
          "primaryKey": false,
          "notNull": true,
          "autoincrement": false
        }
      },
      "indexes": {
        "quiz_attempts_session_idx": {
          "name": "quiz_attempts_session_idx",
          "columns": [
            "session_id"
          ],
          "isUnique": false
        },
        "quiz_attempts_card_progress_idx": {
          "name": "quiz_attempts_card_progress_idx",
          "columns": [
            "card_progress_id"
          ],
          "isUnique": false
        }
      },
      "foreignKeys": {
        "quiz_attempts_session_id_quiz_sessions_id_fk": {
          "name": "quiz_attempts_session_id_quiz_sessions_id_fk",
          "tableFrom": "quiz_attempts",
          "tableTo": "quiz_sessions",
          "columnsFrom": [
            "session_id"
          ],
          "columnsTo": [
            "id"
          ],
          "onDelete": "cascade",
          "onUpdate": "no action"
        },
        "quiz_attempts_card_progress_id_card_progress_id_fk": {
          "name": "quiz_attempts_card_progress_id_card_progress_id_fk",
          "tableFrom": "quiz_attempts",
          "tableTo": "card_progress",
          "columnsFrom": [
            "card_progress_id"
          ],
          "columnsTo": [
            "id"
          ],
          "onDelete": "no action",
          "onUpdate": "no action"
        },
        "quiz_attempts_word_id_words_id_fk": {
          "name": "quiz_attempts_word_id_words_id_fk",
          "tableFrom": "quiz_attempts",
          "tableTo": "words",
          "columnsFrom": [
            "word_id"
          ],
          "columnsTo": [
            "id"
          ],
          "onDelete": "no action",
          "onUpdate": "no action"
        }
      },
      "compositePrimaryKeys": {},
      "uniqueConstraints": {},
      "checkConstraints": {}
    },
    "quiz_sessions": {
      "name": "quiz_sessions",
      "columns": {
        "id": {
          "name": "id",
          "type": "integer",
          "primaryKey": true,
          "notNull": true,
          "autoincrement": true
        },
        "user_id": {
          "name": "user_id",
          "type": "integer",
          "primaryKey": false,
          "notNull": true,
          "autoincrement": false
        },
        "started_at": {
          "name": "started_at",
          "type": "integer",
          "primaryKey": false,
          "notNull": true,
          "autoincrement": false
        },
        "ended_at": {
          "name": "ended_at",
          "type": "integer",
          "primaryKey": false,
          "notNull": false,
          "autoincrement": false
        },
        "words_attempted": {
          "name": "words_attempted",
          "type": "integer",
          "primaryKey": false,
          "notNull": true,
          "autoincrement": false,
          "default": 0
        },
        "words_correct": {
          "name": "words_correct",
          "type": "integer",
          "primaryKey": false,
          "notNull": true,
          "autoincrement": false,
          "default": 0
        },
        "session_type": {
          "name": "session_type",
          "type": "text",
          "primaryKey": false,
          "notNull": true,
          "autoincrement": false,
          "default": "'practice'"
        },
        "category_id": {
          "name": "category_id",
          "type": "integer",
          "primaryKey": false,
          "notNull": false,
          "autoincrement": false
        }
      },
      "indexes": {
        "quiz_sessions_user_id_idx": {
          "name": "quiz_sessions_user_id_idx",
          "columns": [
            "user_id"
          ],
          "isUnique": false
        }
      },
      "foreignKeys": {
        "quiz_sessions_user_id_user_profile_id_fk": {
          "name": "quiz_sessions_user_id_user_profile_id_fk",
          "tableFrom": "quiz_sessions",
          "tableTo": "user_profile",
          "columnsFrom": [
            "user_id"
          ],
          "columnsTo": [
            "id"
          ],
          "onDelete": "cascade",
          "onUpdate": "no action"
        },
        "quiz_sessions_category_id_word_categories_id_fk": {
          "name": "quiz_sessions_category_id_word_categories_id_fk",
          "tableFrom": "quiz_sessions",
          "tableTo": "word_categories",
          "columnsFrom": [
            "category_id"
          ],
          "columnsTo": [
            "id"
          ],
          "onDelete": "no action",
          "onUpdate": "no action"
        }
      },
      "compositePrimaryKeys": {},
      "uniqueConstraints": {},
      "checkConstraints": {}
    },
    "user_profile": {
      "name": "user_profile",
      "columns": {
        "id": {
          "name": "id",
          "type": "integer",
          "primaryKey": true,
          "notNull": true,
          "autoincrement": true
        },
        "name": {
          "name": "name",
          "type": "text",
          "primaryKey": false,
          "notNull": true,
          "autoincrement": false,
          "default": "'Player'"
        },
        "created_at": {
          "name": "created_at",
          "type": "integer",
          "primaryKey": false,
          "notNull": true,
          "autoincrement": false
        },
        "settings": {
          "name": "settings",
          "type": "text",
          "primaryKey": false,
          "notNull": false,
          "autoincrement": false
        }
      },
      "indexes": {},
      "foreignKeys": {},
      "compositePrimaryKeys": {},
      "uniqueConstraints": {},
      "checkConstraints": {}
    },
    "user_stats": {
      "name": "user_stats",
      "columns": {
        "user_id": {
          "name": "user_id",
          "type": "integer",
          "primaryKey": true,
          "notNull": true,
          "autoincrement": false
        },
        "current_streak": {
          "name": "current_streak",
          "type": "integer",
          "primaryKey": false,
          "notNull": true,
          "autoincrement": false,
          "default": 0
        },
        "longest_streak": {
          "name": "longest_streak",
          "type": "integer",
          "primaryKey": false,
          "notNull": true,
          "autoincrement": false,
          "default": 0
        },
        "last_practice_date": {
          "name": "last_practice_date",
          "type": "integer",
          "primaryKey": false,
          "notNull": false,
          "autoincrement": false
        },
        "total_words_learned": {
          "name": "total_words_learned",
          "type": "integer",
          "primaryKey": false,
          "notNull": true,
          "autoincrement": false,
          "default": 0
        },
        "total_quizzes": {
          "name": "total_quizzes",
          "type": "integer",
          "primaryKey": false,
          "notNull": true,
          "autoincrement": false,
          "default": 0
        },
        "total_correct": {
          "name": "total_correct",
          "type": "integer",
          "primaryKey": false,
          "notNull": true,
          "autoincrement": false,
          "default": 0
        },
        "total_attempts": {
          "name": "total_attempts",
          "type": "integer",
          "primaryKey": false,
          "notNull": true,
          "autoincrement": false,
          "default": 0
        },
        "xp_points": {
          "name": "xp_points",
          "type": "integer",
          "primaryKey": false,
          "notNull": true,
          "autoincrement": false,
          "default": 0
        },
        "level": {
          "name": "level",
          "type": "integer",
          "primaryKey": false,
          "notNull": true,
          "autoincrement": false,
          "default": 1
        }
      },
      "indexes": {},
      "foreignKeys": {
        "user_stats_user_id_user_profile_id_fk": {
          "name": "user_stats_user_id_user_profile_id_fk",
          "tableFrom": "user_stats",
          "tableTo": "user_profile",
          "columnsFrom": [
            "user_id"
          ],
          "columnsTo": [
            "id"
          ],
          "onDelete": "cascade",
          "onUpdate": "no action"
        }
      },
      "compositePrimaryKeys": {},
      "uniqueConstraints": {},
      "checkConstraints": {}
    },
    "word_categories": {
      "name": "word_categories",
      "columns": {
        "id": {
          "name": "id",
          "type": "integer",
          "primaryKey": true,
          "notNull": true,
          "autoincrement": true
        },
        "name": {
          "name": "name",
          "type": "text",
          "primaryKey": false,
          "notNull": true,
          "autoincrement": false
        },
        "description": {
          "name": "description",
          "type": "text",
          "primaryKey": false,
          "notNull": false,
          "autoincrement": false
        }
      },
      "indexes": {
        "word_categories_name_unique": {
          "name": "word_categories_name_unique",
          "columns": [
            "name"
          ],
          "isUnique": true
        }
      },
      "foreignKeys": {},
      "compositePrimaryKeys": {},
      "uniqueConstraints": {},
      "checkConstraints": {}
    },
    "word_category_mapping": {
      "name": "word_category_mapping",
      "columns": {
        "word_id": {
          "name": "word_id",
          "type": "integer",
          "primaryKey": false,
          "notNull": true,
          "autoincrement": false
        },
        "category_id": {
          "name": "category_id",
          "type": "integer",
          "primaryKey": false,
          "notNull": true,
          "autoincrement": false
        }
      },
      "indexes": {
        "word_category_unique": {
          "name": "word_category_unique",
          "columns": [
            "word_id",
            "category_id"
          ],
          "isUnique": true
        }
      },
      "foreignKeys": {
        "word_category_mapping_word_id_words_id_fk": {
          "name": "word_category_mapping_word_id_words_id_fk",
          "tableFrom": "word_category_mapping",
          "tableTo": "words",
          "columnsFrom": [
            "word_id"
          ],
          "columnsTo": [
            "id"
          ],
          "onDelete": "cascade",
          "onUpdate": "no action"
        },
        "word_category_mapping_category_id_word_categories_id_fk": {
          "name": "word_category_mapping_category_id_word_categories_id_fk",
          "tableFrom": "word_category_mapping",
          "tableTo": "word_categories",
          "columnsFrom": [
            "category_id"
          ],
          "columnsTo": [
            "id"
          ],
          "onDelete": "cascade",
          "onUpdate": "no action"
        }
      },
      "compositePrimaryKeys": {},
      "uniqueConstraints": {},
      "checkConstraints": {}
    },
    "words": {
      "name": "words",
      "columns": {
        "id": {
          "name": "id",
          "type": "integer",
          "primaryKey": true,
          "notNull": true,
          "autoincrement": true
        },
        "word": {
          "name": "word",
          "type": "text",
          "primaryKey": false,
          "notNull": true,
          "autoincrement": false
        },
        "definition": {
          "name": "definition",
          "type": "text",
          "primaryKey": false,
          "notNull": true,
          "autoincrement": false
        },
        "part_of_speech": {
          "name": "part_of_speech",
          "type": "text",
          "primaryKey": false,
          "notNull": false,
          "autoincrement": false
        },
        "pronunciation": {
          "name": "pronunciation",
          "type": "text",
          "primaryKey": false,
          "notNull": false,
          "autoincrement": false
        },
        "audio_url": {
          "name": "audio_url",
          "type": "text",
          "primaryKey": false,
          "notNull": false,
          "autoincrement": false
        },
        "etymology": {
          "name": "etymology",
          "type": "text",
          "primaryKey": false,
          "notNull": false,
          "autoincrement": false
        },
        "example_sentence": {
          "name": "example_sentence",
          "type": "text",
          "primaryKey": false,
          "notNull": false,
          "autoincrement": false
        },
        "difficulty": {
          "name": "difficulty",
          "type": "integer",
          "primaryKey": false,
          "notNull": true,
          "autoincrement": false,
          "default": 1000
        },
        "language": {
          "name": "language",
          "type": "text",
          "primaryKey": false,
          "notNull": true,
          "autoincrement": false,
          "default": "'en'"
        },
        "syllable_count": {
          "name": "syllable_count",
          "type": "integer",
          "primaryKey": false,
          "notNull": false,
          "autoincrement": false
        },
        "imported_at": {
          "name": "imported_at",
          "type": "integer",
          "primaryKey": false,
          "notNull": true,
          "autoincrement": false
        }
      },
      "indexes": {
        "words_word_unique": {
          "name": "words_word_unique",
          "columns": [
            "word"
          ],
          "isUnique": true
        },
        "words_word_idx": {
          "name": "words_word_idx",
          "columns": [
            "word"
          ],
          "isUnique": false
        },
        "words_difficulty_idx": {
          "name": "words_difficulty_idx",
          "columns": [
            "difficulty"
          ],
          "isUnique": false
        }
      },
      "foreignKeys": {},
      "compositePrimaryKeys": {},
      "uniqueConstraints": {},
      "checkConstraints": {}
    }
  },
  "views": {},
  "enums": {},
  "_meta": {
    "schemas": {},
    "tables": {},
    "columns": {}
  },
  "internal": {
    "indexes": {}
  }
}